<?xml version="1.0" encoding="utf-8" ?>
<dwsync>
<file name="home.html" server="198.100.155.100:990/ass4/" local="130618835331203953" remote="130618835360000000" Dst="1" />
<file name="login.html" server="198.100.155.100:990/ass4/" local="130618808306438225" remote="130618808330000000" Dst="1" />
<file name="logout.html" server="198.100.155.100:990/ass4/" local="130618682382525789" remote="130618682400000000" Dst="1" />
<file name="marvel.html" server="198.100.155.100:990/ass4/" local="130618762454115622" remote="130618762480000000" Dst="1" />
<file name="comics.html" server="198.100.155.100:990/ass4/" local="130618771843972691" remote="130618772220000000" Dst="1" />
<file name="user.html" server="198.100.155.100:990/ass4/" local="130618822198902829" remote="130618822230000000" Dst="1" />
<file name="signup.html" server="198.100.155.100:990/ass4/" local="130618827643104219" remote="130618827670000000" Dst="1" />
<file name="users.html" server="198.100.155.100:990/ass4/" local="130618835528405233" remote="130618835550000000" Dst="1" />
</dwsync>